picgrab.py
picgrab-0.1.dist-info/LICENSE
picgrab-0.1.dist-info/METADATA
picgrab-0.1.dist-info/WHEEL
picgrab-0.1.dist-info/entry_points.txt
picgrab-0.1.dist-info/top_level.txt
picgrab-0.1.dist-info/RECORD
