Metadata-Version: 2.1
Name: picgrab
Version: 0.1
Summary: A script to download images from web pages
Home-page: https://twitter.com/Lanaev0li
Author: Avinion
Author-email: shizofrin@gmail.com
License: Avinion Group
Classifier: Programming Language :: Python :: 3
Classifier: License :: OSI Approved :: MIT License
Classifier: Operating System :: OS Independent
License-File: LICENSE
Requires-Dist: requests
Requires-Dist: beautifulsoup4
Requires-Dist: tqdm
